calculator_framework/api/README.md
calculator_framework/api/__init__.py
calculator_framework/api/core.py
calculator_api_app-0.5.1.dist-info/METADATA
calculator_api_app-0.5.1.dist-info/WHEEL
calculator_api_app-0.5.1.dist-info/RECORD
