Metadata-Version: 2.3
Name: calculator_api_app
Version: 0.5.1
Summary: A FastAPI app for calculator framework
License: MIT
Author: DSAI
Author-email: dsai@bma.bm
Requires-Python: >=3.11,<4.0
Classifier: License :: OSI Approved :: MIT License
Classifier: Programming Language :: Python :: 3
Classifier: Programming Language :: Python :: 3.11
Classifier: Programming Language :: Python :: 3.12
Classifier: Programming Language :: Python :: 3.13
Requires-Dist: fastapi (>=0.89.1,<0.90.0)
Requires-Dist: pydantic (>=1.10.0,<2.0.0)
Requires-Dist: uvicorn (>=0.20.0,<0.21.0)
Project-URL: Homepage, https://github.com/Bermuda-Monetary-Authority
Project-URL: Repository, https://github.com/Bermuda-Monetary-Authority
